face_detect/__init__.py
face_detect/faceextractionurl.py
face_extraction/__init__.py
face_extraction/getFace.py
face_extraction-0.0.4.dist-info/LICENSE
face_extraction-0.0.4.dist-info/METADATA
face_extraction-0.0.4.dist-info/WHEEL
face_extraction-0.0.4.dist-info/top_level.txt
face_extraction-0.0.4.dist-info/RECORD
