Metadata-Version: 2.1
Name: face-extraction
Version: 0.0.4
Summary: To extract face out of an image
Home-page: https://github.com/pypa/sampleproject
Author: Muskan Gupta
Author-email: guptamuskan495@gmail.com
License: UNKNOWN
Project-URL: Bug Tracker, https://github.com/pypa/sampleproject/issues
Platform: UNKNOWN
Classifier: Programming Language :: Python :: 3
Classifier: License :: OSI Approved :: MIT License
Classifier: Operating System :: OS Independent
Requires-Python: >=3.6
Requires-Dist: opencv-python
Requires-Dist: Pillow
Requires-Dist: numpy
Requires-Dist: requests
